[{"firstName":" Starlin","lastName":"Castro","address":{"zipCode":"60613","country":"USA","city":"Chicago","street":"1060 West Addison Street","state":"IL"},"personCode":"944c","email":[[Ljava.lang.String;@610455d6]},{"firstName":" Brock","lastName":"Sampson","address":{"zipCode":"68116","country":"USA","city":"Omaha","street":"123 N 1st Street","state":"NE"},"personCode":"306a","email":[[Ljava.lang.String;@511d50c0]},{"firstName":" Miles","lastName":"O'Brien","address":{"zipCode":"75001","country":"USA","city":"Dallas","street":"8753 West 3rd Ave.","state":"TX"},"personCode":"55bb","email":[[Ljava.lang.String;@60e53b93]},{"firstName":" Miles","lastName":"O'Brien","address":{"zipCode":"K1A 0G9","country":"Canada","city":"Ottawa","street":"123 Friendly Street","state":"ON"},"personCode":"2342","email":[null]},{"firstName":" Gordon","lastName":"Gekko","address":{"zipCode":"10005-0012","country":"USA","city":"New York","street":"1 Wall Street","state":"NY"},"personCode":"aef1","email":[null]},{"firstName":" Bud","lastName":"Fox","address":{"zipCode":"10004","country":"USA","city":"New York","street":"321 Bronx Street","state":"NY"},"personCode":"321f","email":[[Ljava.lang.String;@5e2de80c]},{"firstName":" Dale","lastName":"Sveum","address":{"zipCode":"60613","country":"USA","city":"Chicago","street":"1060 West Addison Street","state":"IL"},"personCode":"ma12","email":[[Ljava.lang.String;@1d44bcfa]},{"firstName":" William","lastName":"Hartnell","address":{"zipCode":"60613","country":"USA","city":"Chicago","street":"1060 West Addison Street","state":"IL"},"personCode":"321nd","email":[[Ljava.lang.String;@266474c2]},{"firstName":" Patrick","lastName":"Troughton","address":{"zipCode":"60613","country":"USA","city":"Chicago","street":"1060 West Addison Street","state":"IL"},"personCode":"nf32a","email":[[Ljava.lang.String;@6f94fa3e]},{"firstName":" Jon","lastName":"Pertwee","address":{"zipCode":" M5V 2T6","country":" Canada","city":" Toronto","street":"301 Front St W","state":" ON"},"personCode":"321na","email":[[Ljava.lang.String;@5e481248]},{"firstName":"Tom","lastName":"Baker","address":{"zipCode":" M5V 1J1","country":" Canada","city":" Toronto","street":"1 Blue Jays Way","state":" ON"},"personCode":"231","email":[[Ljava.lang.String;@66d3c617]},{"firstName":" Richard","lastName":"Hurndall","address":{"zipCode":"","country":" Mexico","city":"Mexico City","street":"Campos El290","state":" FD"},"personCode":"6doc","email":[[Ljava.lang.String;@63947c6b]},{"firstName":" C.","lastName":"Baker","address":{"zipCode":"68503","country":"USA","city":"Lincoln","street":"Avery Hall","state":"NE"},"personCode":"321dr","email":[[Ljava.lang.String;@2b193f2d]},{"firstName":"Sylvester","lastName":"McCoy","address":{"zipCode":"11368","country":"USA","city":" Flushing","street":"126-01 Roosevelt Ave","state":" NY"},"personCode":"1svndr","email":[[Ljava.lang.String;@355da254]},{"firstName":" Paul","lastName":"McGann","address":{"zipCode":"07073","country":"USA","city":" East Rutherford","street":"1 MetLife Stadium Dr","state":" NJ"},"personCode":"123lst","email":[[Ljava.lang.String;@4dc63996]},{"firstName":" Chris","lastName":"Eccleston","address":{"zipCode":"10451","country":"USA","city":" Bronx","street":"1 E 161st St","state":" NY"},"personCode":"nwdoc1","email":[[Ljava.lang.String;@d716361]},{"firstName":" David","lastName":"Tennant","address":{"zipCode":" 60611","country":"USA","city":" Chicago","street":"700 E Grand Ave","state":" IL"},"personCode":"2ndbestd","email":[[Ljava.lang.String;@6ff3c5b5]},{"firstName":" Matt","lastName":"Smith","address":{"zipCode":"60616","country":"USA","city":" Chicago","street":"333 W 35th St","state":" IL"},"personCode":"wrddoc","email":[[Ljava.lang.String;@3764951d]},{"firstName":" Kaylee","lastName":"Ehrmantraut","address":{"zipCode":" 87105","country":"USA","city":" Albuquerque","street":"800 West 7th Street","state":" NM"},"personCode":"bbchar","email":[null]},{"firstName":" Peter","lastName":"Davison","address":{"zipCode":" ","country":" Mexico","city":" Los Cabos","street":"123 Cabo San Lucas","state":" BCS"},"personCode":"doc05","email":[null]}]